CHANGES.rst
DESCRIPTION.rst
LICENSE
MANIFEST.in
README.md
setup.py
src/wai.annotations.audio.egg-info/PKG-INFO
src/wai.annotations.audio.egg-info/SOURCES.txt
src/wai.annotations.audio.egg-info/dependency_links.txt
src/wai.annotations.audio.egg-info/entry_points.txt
src/wai.annotations.audio.egg-info/namespace_packages.txt
src/wai.annotations.audio.egg-info/requires.txt
src/wai.annotations.audio.egg-info/top_level.txt
src/wai/annotations/audio/__init__.py
src/wai/annotations/audio/format/__init__.py
src/wai/annotations/audio/format/audio_info/__init__.py
src/wai/annotations/audio/format/audio_info/component/_AudioInfo.py
src/wai/annotations/audio/format/audio_info/component/__init__.py
src/wai/annotations/audio/format/audio_info/specifier/_AudioInfoACOutputFormatSpecifier.py
src/wai/annotations/audio/format/audio_info/specifier/_AudioInfoOutputFormatSpecifier.py
src/wai/annotations/audio/format/audio_info/specifier/_AudioInfoSPOutputFormatSpecifier.py
src/wai/annotations/audio/format/audio_info/specifier/__init__.py
src/wai/annotations/audio/isp/__init__.py
src/wai/annotations/audio/isp/base_augmentation/_BaseAudioAugmentation.py
src/wai/annotations/audio/isp/base_augmentation/__init__.py
src/wai/annotations/audio/isp/convert_to_mono/component/_ConvertToMono.py
src/wai/annotations/audio/isp/convert_to_mono/component/__init__.py
src/wai/annotations/audio/isp/convert_to_mono/specifier/_ConvertToMonoISPSpecifier.py
src/wai/annotations/audio/isp/convert_to_mono/specifier/__init__.py
src/wai/annotations/audio/isp/convert_to_wav/__init__.py
src/wai/annotations/audio/isp/convert_to_wav/component/_ConvertToWav.py
src/wai/annotations/audio/isp/convert_to_wav/component/__init__.py
src/wai/annotations/audio/isp/convert_to_wav/specifier/_ConvertToWavISPSpecifier.py
src/wai/annotations/audio/isp/convert_to_wav/specifier/__init__.py
src/wai/annotations/audio/isp/pitch_shift/component/_PitchShift.py
src/wai/annotations/audio/isp/pitch_shift/component/__init__.py
src/wai/annotations/audio/isp/pitch_shift/specifier/_PitchShiftISPSpecifier.py
src/wai/annotations/audio/isp/pitch_shift/specifier/__init__.py
src/wai/annotations/audio/isp/resample/component/_ReseampleAudio.py
src/wai/annotations/audio/isp/resample/component/__init__.py
src/wai/annotations/audio/isp/resample/specifier/_ResampleAudioISPSpecifier.py
