Metadata-Version: 2.1
Name: wai.annotations.audio
Version: 1.0.1
Summary: Module with audio plugins for wai.annotations.
Home-page: https://github.com/waikato-datamining/wai-annotations-audio
Author: Peter Reutemann
Author-email: fracpete@waikato.ac.nz
License: Apache License Version 2.0
Classifier: Development Status :: 4 - Beta
Classifier: License :: OSI Approved :: Apache Software License
Classifier: Topic :: Scientific/Engineering :: Mathematics
Classifier: Programming Language :: Python :: 3
License-File: LICENSE
